<annotation>
	<folder></folder>
	<filename>14af9bdd-1a9a-4f1f-bd44-daa948afdb40_png_jpg.rf.a015e117abe71025256e316f085ecc4f.jpg</filename>
	<path>14af9bdd-1a9a-4f1f-bd44-daa948afdb40_png_jpg.rf.a015e117abe71025256e316f085ecc4f.jpg</path>
	<source>
		<database>roboflow.com</database>
	</source>
	<size>
		<width>1024</width>
		<height>1024</height>
		<depth>3</depth>
	</size>
	<segmented>0</segmented>
	<object>
		<name>radio</name>
		<pose>Unspecified</pose>
		<truncated>0</truncated>
		<difficult>0</difficult>
		<occluded>0</occluded>
		<bndbox>
			<xmin>72</xmin>
			<xmax>101</xmax>
			<ymin>203</ymin>
			<ymax>245</ymax>
		</bndbox>
	</object>
	<object>
		<name>radio</name>
		<pose>Unspecified</pose>
		<truncated>0</truncated>
		<difficult>0</difficult>
		<occluded>0</occluded>
		<bndbox>
			<xmin>209</xmin>
			<xmax>242</xmax>
			<ymin>199</ymin>
			<ymax>247</ymax>
		</bndbox>
	</object>
	<object>
		<name>radio</name>
		<pose>Unspecified</pose>
		<truncated>0</truncated>
		<difficult>0</difficult>
		<occluded>0</occluded>
		<bndbox>
			<xmin>351</xmin>
			<xmax>377</xmax>
			<ymin>204</ymin>
			<ymax>244</ymax>
		</bndbox>
	</object>
	<object>
		<name>checkbox</name>
		<pose>Unspecified</pose>
		<truncated>0</truncated>
		<difficult>0</difficult>
		<occluded>0</occluded>
		<bndbox>
			<xmin>210</xmin>
			<xmax>239</xmax>
			<ymin>148</ymin>
			<ymax>185</ymax>
		</bndbox>
	</object>
	<object>
		<name>checkbox</name>
		<pose>Unspecified</pose>
		<truncated>0</truncated>
		<difficult>0</difficult>
		<occluded>0</occluded>
		<bndbox>
			<xmin>351</xmin>
			<xmax>380</xmax>
			<ymin>148</ymin>
			<ymax>188</ymax>
		</bndbox>
	</object>
	<object>
		<name>dropdown</name>
		<pose>Unspecified</pose>
		<truncated>0</truncated>
		<difficult>0</difficult>
		<occluded>0</occluded>
		<bndbox>
			<xmin>75</xmin>
			<xmax>289</xmax>
			<ymin>395</ymin>
			<ymax>458</ymax>
		</bndbox>
	</object>
	<object>
		<name>dropdown</name>
		<pose>Unspecified</pose>
		<truncated>0</truncated>
		<difficult>0</difficult>
		<occluded>0</occluded>
		<bndbox>
			<xmin>75</xmin>
			<xmax>287</xmax>
			<ymin>551</ymin>
			<ymax>610</ymax>
		</bndbox>
	</object>
	<object>
		<name>dropdown</name>
		<pose>Unspecified</pose>
		<truncated>0</truncated>
		<difficult>0</difficult>
		<occluded>0</occluded>
		<bndbox>
			<xmin>630</xmin>
			<xmax>764</xmax>
			<ymin>366</ymin>
			<ymax>426</ymax>
		</bndbox>
	</object>
	<object>
		<name>checkbox</name>
		<pose>Unspecified</pose>
		<truncated>0</truncated>
		<difficult>0</difficult>
		<occluded>0</occluded>
		<bndbox>
			<xmin>73</xmin>
			<xmax>99</xmax>
			<ymin>151</ymin>
			<ymax>183</ymax>
		</bndbox>
	</object>
	<object>
		<name>input</name>
		<pose>Unspecified</pose>
		<truncated>0</truncated>
		<difficult>0</difficult>
		<occluded>0</occluded>
		<bndbox>
			<xmin>349</xmin>
			<xmax>559</xmax>
			<ymin>395</ymin>
			<ymax>461</ymax>
		</bndbox>
	</object>
	<object>
		<name>input</name>
		<pose>Unspecified</pose>
		<truncated>0</truncated>
		<difficult>0</difficult>
		<occluded>0</occluded>
		<bndbox>
			<xmin>346</xmin>
			<xmax>560</xmax>
			<ymin>698</ymin>
			<ymax>765</ymax>
		</bndbox>
	</object>
	<object>
		<name>input</name>
		<pose>Unspecified</pose>
		<truncated>0</truncated>
		<difficult>0</difficult>
		<occluded>0</occluded>
		<bndbox>
			<xmin>349</xmin>
			<xmax>518</xmax>
			<ymin>826</ymin>
			<ymax>887</ymax>
		</bndbox>
	</object>
	<object>
		<name>label</name>
		<pose>Unspecified</pose>
		<truncated>0</truncated>
		<difficult>0</difficult>
		<occluded>0</occluded>
		<bndbox>
			<xmin>345</xmin>
			<xmax>424</xmax>
			<ymin>669</ymin>
			<ymax>690</ymax>
		</bndbox>
	</object>
	<object>
		<name>label</name>
		<pose>Unspecified</pose>
		<truncated>0</truncated>
		<difficult>0</difficult>
		<occluded>0</occluded>
		<bndbox>
			<xmin>342</xmin>
			<xmax>424</xmax>
			<ymin>518</ymin>
			<ymax>540</ymax>
		</bndbox>
	</object>
	<object>
		<name>label</name>
		<pose>Unspecified</pose>
		<truncated>0</truncated>
		<difficult>0</difficult>
		<occluded>0</occluded>
		<bndbox>
			<xmin>72</xmin>
			<xmax>111</xmax>
			<ymin>515</ymin>
			<ymax>536</ymax>
		</bndbox>
	</object>
	<object>
		<name>label</name>
		<pose>Unspecified</pose>
		<truncated>0</truncated>
		<difficult>0</difficult>
		<occluded>0</occluded>
		<bndbox>
			<xmin>71</xmin>
			<xmax>114</xmax>
			<ymin>362</ymin>
			<ymax>384</ymax>
		</bndbox>
	</object>
	<object>
		<name>label</name>
		<pose>Unspecified</pose>
		<truncated>0</truncated>
		<difficult>0</difficult>
		<occluded>0</occluded>
		<bndbox>
			<xmin>341</xmin>
			<xmax>427</xmax>
			<ymin>363</ymin>
			<ymax>389</ymax>
		</bndbox>
	</object>
	<object>
		<name>icon</name>
		<pose>Unspecified</pose>
		<truncated>0</truncated>
		<difficult>0</difficult>
		<occluded>0</occluded>
		<bndbox>
			<xmin>534</xmin>
			<xmax>550</xmax>
			<ymin>154</ymin>
			<ymax>180</ymax>
		</bndbox>
	</object>
	<object>
		<name>icon</name>
		<pose>Unspecified</pose>
		<truncated>0</truncated>
		<difficult>0</difficult>
		<occluded>0</occluded>
		<bndbox>
			<xmin>534</xmin>
			<xmax>547</xmax>
			<ymin>206</ymin>
			<ymax>227</ymax>
		</bndbox>
	</object>
	<object>
		<name>icon</name>
		<pose>Unspecified</pose>
		<truncated>0</truncated>
		<difficult>0</difficult>
		<occluded>0</occluded>
		<bndbox>
			<xmin>578</xmin>
			<xmax>591</xmax>
			<ymin>159</ymin>
			<ymax>178</ymax>
		</bndbox>
	</object>
	<object>
		<name>icon</name>
		<pose>Unspecified</pose>
		<truncated>0</truncated>
		<difficult>0</difficult>
		<occluded>0</occluded>
		<bndbox>
			<xmin>582</xmin>
			<xmax>592</xmax>
			<ymin>205</ymin>
			<ymax>226</ymax>
		</bndbox>
	</object>
	<object>
		<name>label</name>
		<pose>Unspecified</pose>
		<truncated>0</truncated>
		<difficult>0</difficult>
		<occluded>0</occluded>
		<bndbox>
			<xmin>105</xmin>
			<xmax>151</xmax>
			<ymin>158</ymin>
			<ymax>177</ymax>
		</bndbox>
	</object>
	<object>
		<name>label</name>
		<pose>Unspecified</pose>
		<truncated>0</truncated>
		<difficult>0</difficult>
		<occluded>0</occluded>
		<bndbox>
			<xmin>103</xmin>
			<xmax>153</xmax>
			<ymin>211</ymin>
			<ymax>231</ymax>
		</bndbox>
	</object>
	<object>
		<name>label</name>
		<pose>Unspecified</pose>
		<truncated>0</truncated>
		<difficult>0</difficult>
		<occluded>0</occluded>
		<bndbox>
			<xmin>243</xmin>
			<xmax>283</xmax>
			<ymin>161</ymin>
			<ymax>178</ymax>
		</bndbox>
	</object>
	<object>
		<name>label</name>
		<pose>Unspecified</pose>
		<truncated>0</truncated>
		<difficult>0</difficult>
		<occluded>0</occluded>
		<bndbox>
			<xmin>245</xmin>
			<xmax>284</xmax>
			<ymin>211</ymin>
			<ymax>234</ymax>
		</bndbox>
	</object>
	<object>
		<name>label</name>
		<pose>Unspecified</pose>
		<truncated>0</truncated>
		<difficult>0</difficult>
		<occluded>0</occluded>
		<bndbox>
			<xmin>387</xmin>
			<xmax>426</xmax>
			<ymin>157</ymin>
			<ymax>177</ymax>
		</bndbox>
	</object>
	<object>
		<name>label</name>
		<pose>Unspecified</pose>
		<truncated>0</truncated>
		<difficult>0</difficult>
		<occluded>0</occluded>
		<bndbox>
			<xmin>384</xmin>
			<xmax>431</xmax>
			<ymin>210</ymin>
			<ymax>232</ymax>
		</bndbox>
	</object>
	<object>
		<name>input</name>
		<pose>Unspecified</pose>
		<truncated>0</truncated>
		<difficult>0</difficult>
		<occluded>0</occluded>
		<bndbox>
			<xmin>345</xmin>
			<xmax>558</xmax>
			<ymin>545</ymin>
			<ymax>613</ymax>
		</bndbox>
	</object>
	<object>
		<name>button</name>
		<pose>Unspecified</pose>
		<truncated>0</truncated>
		<difficult>0</difficult>
		<occluded>0</occluded>
		<bndbox>
			<xmin>632</xmin>
			<xmax>855</xmax>
			<ymin>492</ymin>
			<ymax>552</ymax>
		</bndbox>
	</object>
	<object>
		<name>button</name>
		<pose>Unspecified</pose>
		<truncated>0</truncated>
		<difficult>0</difficult>
		<occluded>0</occluded>
		<bndbox>
			<xmin>74</xmin>
			<xmax>290</xmax>
			<ymin>688</ymin>
			<ymax>746</ymax>
		</bndbox>
	</object>
</annotation>
