<annotation>
	<folder></folder>
	<filename>48d77ecf-07c3-4186-bf64-a662e41475bf_png_jpg.rf.9e66235a3c19ca69793a0a0d5f6c8f6f.jpg</filename>
	<path>48d77ecf-07c3-4186-bf64-a662e41475bf_png_jpg.rf.9e66235a3c19ca69793a0a0d5f6c8f6f.jpg</path>
	<source>
		<database>roboflow.com</database>
	</source>
	<size>
		<width>1024</width>
		<height>1024</height>
		<depth>3</depth>
	</size>
	<segmented>0</segmented>
	<object>
		<name>checkbox</name>
		<pose>Unspecified</pose>
		<truncated>0</truncated>
		<difficult>0</difficult>
		<occluded>0</occluded>
		<bndbox>
			<xmin>422</xmin>
			<xmax>449</xmax>
			<ymin>351</ymin>
			<ymax>401</ymax>
		</bndbox>
	</object>
	<object>
		<name>checkbox</name>
		<pose>Unspecified</pose>
		<truncated>0</truncated>
		<difficult>0</difficult>
		<occluded>0</occluded>
		<bndbox>
			<xmin>421</xmin>
			<xmax>448</xmax>
			<ymin>447</ymin>
			<ymax>493</ymax>
		</bndbox>
	</object>
	<object>
		<name>checkbox</name>
		<pose>Unspecified</pose>
		<truncated>0</truncated>
		<difficult>0</difficult>
		<occluded>0</occluded>
		<bndbox>
			<xmin>422</xmin>
			<xmax>448</xmax>
			<ymin>535</ymin>
			<ymax>583</ymax>
		</bndbox>
	</object>
	<object>
		<name>checkbox</name>
		<pose>Unspecified</pose>
		<truncated>0</truncated>
		<difficult>0</difficult>
		<occluded>0</occluded>
		<bndbox>
			<xmin>420</xmin>
			<xmax>448</xmax>
			<ymin>624</ymin>
			<ymax>669</ymax>
		</bndbox>
	</object>
	<object>
		<name>checkbox</name>
		<pose>Unspecified</pose>
		<truncated>0</truncated>
		<difficult>0</difficult>
		<occluded>0</occluded>
		<bndbox>
			<xmin>420</xmin>
			<xmax>448</xmax>
			<ymin>713</ymin>
			<ymax>758</ymax>
		</bndbox>
	</object>
	<object>
		<name>dropdown</name>
		<pose>Unspecified</pose>
		<truncated>0</truncated>
		<difficult>0</difficult>
		<occluded>0</occluded>
		<bndbox>
			<xmin>406</xmin>
			<xmax>647</xmax>
			<ymin>135</ymin>
			<ymax>261</ymax>
		</bndbox>
	</object>
</annotation>
