<annotation>
	<folder></folder>
	<filename>71bb65d9-2d40-4504-aa2f-3229eb784f3f_png_jpg.rf.a9f19b154151f95412209d05a213fe48.jpg</filename>
	<path>71bb65d9-2d40-4504-aa2f-3229eb784f3f_png_jpg.rf.a9f19b154151f95412209d05a213fe48.jpg</path>
	<source>
		<database>roboflow.com</database>
	</source>
	<size>
		<width>1024</width>
		<height>1024</height>
		<depth>3</depth>
	</size>
	<segmented>0</segmented>
	<object>
		<name>radio</name>
		<pose>Unspecified</pose>
		<truncated>0</truncated>
		<difficult>0</difficult>
		<occluded>0</occluded>
		<bndbox>
			<xmin>294</xmin>
			<xmax>321</xmax>
			<ymin>550</ymin>
			<ymax>597</ymax>
		</bndbox>
	</object>
	<object>
		<name>radio</name>
		<pose>Unspecified</pose>
		<truncated>0</truncated>
		<difficult>0</difficult>
		<occluded>0</occluded>
		<bndbox>
			<xmin>317</xmin>
			<xmax>346</xmax>
			<ymin>642</ymin>
			<ymax>678</ymax>
		</bndbox>
	</object>
	<object>
		<name>radio</name>
		<pose>Unspecified</pose>
		<truncated>0</truncated>
		<difficult>0</difficult>
		<occluded>0</occluded>
		<bndbox>
			<xmin>317</xmin>
			<xmax>353</xmax>
			<ymin>789</ymin>
			<ymax>826</ymax>
		</bndbox>
	</object>
	<object>
		<name>radio</name>
		<pose>Unspecified</pose>
		<truncated>0</truncated>
		<difficult>0</difficult>
		<occluded>0</occluded>
		<bndbox>
			<xmin>318</xmin>
			<xmax>351</xmax>
			<ymin>693</ymin>
			<ymax>739</ymax>
		</bndbox>
	</object>
	<object>
		<name>radio</name>
		<pose>Unspecified</pose>
		<truncated>0</truncated>
		<difficult>0</difficult>
		<occluded>0</occluded>
		<bndbox>
			<xmin>314</xmin>
			<xmax>351</xmax>
			<ymin>833</ymin>
			<ymax>884</ymax>
		</bndbox>
	</object>
	<object>
		<name>checkbox</name>
		<pose>Unspecified</pose>
		<truncated>0</truncated>
		<difficult>0</difficult>
		<occluded>0</occluded>
		<bndbox>
			<xmin>184</xmin>
			<xmax>210</xmax>
			<ymin>401</ymin>
			<ymax>443</ymax>
		</bndbox>
	</object>
	<object>
		<name>checkbox</name>
		<pose>Unspecified</pose>
		<truncated>0</truncated>
		<difficult>0</difficult>
		<occluded>0</occluded>
		<bndbox>
			<xmin>189</xmin>
			<xmax>221</xmax>
			<ymin>931</ymin>
			<ymax>965</ymax>
		</bndbox>
	</object>
	<object>
		<name>button</name>
		<pose>Unspecified</pose>
		<truncated>0</truncated>
		<difficult>0</difficult>
		<occluded>0</occluded>
		<bndbox>
			<xmin>420</xmin>
			<xmax>650</xmax>
			<ymin>404</ymin>
			<ymax>450</ymax>
		</bndbox>
	</object>
	<object>
		<name>button</name>
		<pose>Unspecified</pose>
		<truncated>0</truncated>
		<difficult>0</difficult>
		<occluded>0</occluded>
		<bndbox>
			<xmin>669</xmin>
			<xmax>900</xmax>
			<ymin>406</ymin>
			<ymax>453</ymax>
		</bndbox>
	</object>
	<object>
		<name>button</name>
		<pose>Unspecified</pose>
		<truncated>0</truncated>
		<difficult>0</difficult>
		<occluded>0</occluded>
		<bndbox>
			<xmin>426</xmin>
			<xmax>656</xmax>
			<ymin>932</ymin>
			<ymax>975</ymax>
		</bndbox>
	</object>
	<object>
		<name>button</name>
		<pose>Unspecified</pose>
		<truncated>0</truncated>
		<difficult>0</difficult>
		<occluded>0</occluded>
		<bndbox>
			<xmin>671</xmin>
			<xmax>904</xmax>
			<ymin>929</ymin>
			<ymax>973</ymax>
		</bndbox>
	</object>
	<object>
		<name>icon</name>
		<pose>Unspecified</pose>
		<truncated>0</truncated>
		<difficult>0</difficult>
		<occluded>0</occluded>
		<bndbox>
			<xmin>910</xmin>
			<xmax>950</xmax>
			<ymin>407</ymin>
			<ymax>452</ymax>
		</bndbox>
	</object>
	<object>
		<name>icon</name>
		<pose>Unspecified</pose>
		<truncated>0</truncated>
		<difficult>0</difficult>
		<occluded>0</occluded>
		<bndbox>
			<xmin>918</xmin>
			<xmax>958</xmax>
			<ymin>921</ymin>
			<ymax>971</ymax>
		</bndbox>
	</object>
</annotation>
