<annotation>
	<folder></folder>
	<filename>8fa9cce1-c286-46eb-a94a-ffd398802cc9_png_jpg.rf.9dcd2457db63ab07730982d2ca1231f8.jpg</filename>
	<path>8fa9cce1-c286-46eb-a94a-ffd398802cc9_png_jpg.rf.9dcd2457db63ab07730982d2ca1231f8.jpg</path>
	<source>
		<database>roboflow.com</database>
	</source>
	<size>
		<width>1024</width>
		<height>1024</height>
		<depth>3</depth>
	</size>
	<segmented>0</segmented>
	<object>
		<name>switch</name>
		<pose>Unspecified</pose>
		<truncated>0</truncated>
		<difficult>0</difficult>
		<occluded>0</occluded>
		<bndbox>
			<xmin>808</xmin>
			<xmax>872</xmax>
			<ymin>324</ymin>
			<ymax>367</ymax>
		</bndbox>
	</object>
	<object>
		<name>switch</name>
		<pose>Unspecified</pose>
		<truncated>0</truncated>
		<difficult>0</difficult>
		<occluded>0</occluded>
		<bndbox>
			<xmin>809</xmin>
			<xmax>874</xmax>
			<ymin>383</ymin>
			<ymax>428</ymax>
		</bndbox>
	</object>
	<object>
		<name>switch</name>
		<pose>Unspecified</pose>
		<truncated>0</truncated>
		<difficult>0</difficult>
		<occluded>0</occluded>
		<bndbox>
			<xmin>808</xmin>
			<xmax>873</xmax>
			<ymin>450</ymin>
			<ymax>492</ymax>
		</bndbox>
	</object>
	<object>
		<name>switch</name>
		<pose>Unspecified</pose>
		<truncated>0</truncated>
		<difficult>0</difficult>
		<occluded>0</occluded>
		<bndbox>
			<xmin>806</xmin>
			<xmax>873</xmax>
			<ymin>861</ymin>
			<ymax>903</ymax>
		</bndbox>
	</object>
	<object>
		<name>switch</name>
		<pose>Unspecified</pose>
		<truncated>0</truncated>
		<difficult>0</difficult>
		<occluded>0</occluded>
		<bndbox>
			<xmin>807</xmin>
			<xmax>871</xmax>
			<ymin>929</ymin>
			<ymax>973</ymax>
		</bndbox>
	</object>
	<object>
		<name>radio</name>
		<pose>Unspecified</pose>
		<truncated>0</truncated>
		<difficult>0</difficult>
		<occluded>0</occluded>
		<bndbox>
			<xmin>548</xmin>
			<xmax>583</xmax>
			<ymin>857</ymin>
			<ymax>902</ymax>
		</bndbox>
	</object>
	<object>
		<name>radio</name>
		<pose>Unspecified</pose>
		<truncated>0</truncated>
		<difficult>0</difficult>
		<occluded>0</occluded>
		<bndbox>
			<xmin>587</xmin>
			<xmax>622</xmax>
			<ymin>856</ymin>
			<ymax>902</ymax>
		</bndbox>
	</object>
	<object>
		<name>radio</name>
		<pose>Unspecified</pose>
		<truncated>0</truncated>
		<difficult>0</difficult>
		<occluded>0</occluded>
		<bndbox>
			<xmin>627</xmin>
			<xmax>663</xmax>
			<ymin>859</ymin>
			<ymax>905</ymax>
		</bndbox>
	</object>
	<object>
		<name>radio</name>
		<pose>Unspecified</pose>
		<truncated>0</truncated>
		<difficult>0</difficult>
		<occluded>0</occluded>
		<bndbox>
			<xmin>667</xmin>
			<xmax>701</xmax>
			<ymin>857</ymin>
			<ymax>902</ymax>
		</bndbox>
	</object>
	<object>
		<name>icon</name>
		<pose>Unspecified</pose>
		<truncated>0</truncated>
		<difficult>0</difficult>
		<occluded>0</occluded>
		<bndbox>
			<xmin>521</xmin>
			<xmax>558</xmax>
			<ymin>117</ymin>
			<ymax>164</ymax>
		</bndbox>
	</object>
	<object>
		<name>icon</name>
		<pose>Unspecified</pose>
		<truncated>0</truncated>
		<difficult>0</difficult>
		<occluded>0</occluded>
		<bndbox>
			<xmin>864</xmin>
			<xmax>906</xmax>
			<ymin>110</ymin>
			<ymax>162</ymax>
		</bndbox>
	</object>
</annotation>
