<annotation>
	<folder></folder>
	<filename>fc8754d7-eabd-4243-8a50-3db62e735b89_png_jpg.rf.11f78c01297e91521aff22d9c4e98645.jpg</filename>
	<path>fc8754d7-eabd-4243-8a50-3db62e735b89_png_jpg.rf.11f78c01297e91521aff22d9c4e98645.jpg</path>
	<source>
		<database>roboflow.com</database>
	</source>
	<size>
		<width>1024</width>
		<height>1024</height>
		<depth>3</depth>
	</size>
	<segmented>0</segmented>
	<object>
		<name>checkbox</name>
		<pose>Unspecified</pose>
		<truncated>0</truncated>
		<difficult>0</difficult>
		<occluded>0</occluded>
		<bndbox>
			<xmin>619</xmin>
			<xmax>641</xmax>
			<ymin>475</ymin>
			<ymax>515</ymax>
		</bndbox>
	</object>
	<object>
		<name>checkbox</name>
		<pose>Unspecified</pose>
		<truncated>0</truncated>
		<difficult>0</difficult>
		<occluded>0</occluded>
		<bndbox>
			<xmin>618</xmin>
			<xmax>640</xmax>
			<ymin>549</ymin>
			<ymax>588</ymax>
		</bndbox>
	</object>
	<object>
		<name>checkbox</name>
		<pose>Unspecified</pose>
		<truncated>0</truncated>
		<difficult>0</difficult>
		<occluded>0</occluded>
		<bndbox>
			<xmin>234</xmin>
			<xmax>258</xmax>
			<ymin>473</ymin>
			<ymax>514</ymax>
		</bndbox>
	</object>
	<object>
		<name>checkbox</name>
		<pose>Unspecified</pose>
		<truncated>0</truncated>
		<difficult>0</difficult>
		<occluded>0</occluded>
		<bndbox>
			<xmin>233</xmin>
			<xmax>257</xmax>
			<ymin>552</ymin>
			<ymax>588</ymax>
		</bndbox>
	</object>
	<object>
		<name>label</name>
		<pose>Unspecified</pose>
		<truncated>0</truncated>
		<difficult>0</difficult>
		<occluded>0</occluded>
		<bndbox>
			<xmin>262</xmin>
			<xmax>381</xmax>
			<ymin>474</ymin>
			<ymax>511</ymax>
		</bndbox>
	</object>
	<object>
		<name>label</name>
		<pose>Unspecified</pose>
		<truncated>0</truncated>
		<difficult>0</difficult>
		<occluded>0</occluded>
		<bndbox>
			<xmin>262</xmin>
			<xmax>382</xmax>
			<ymin>544</ymin>
			<ymax>588</ymax>
		</bndbox>
	</object>
	<object>
		<name>label</name>
		<pose>Unspecified</pose>
		<truncated>0</truncated>
		<difficult>0</difficult>
		<occluded>0</occluded>
		<bndbox>
			<xmin>647</xmin>
			<xmax>798</xmax>
			<ymin>474</ymin>
			<ymax>513</ymax>
		</bndbox>
	</object>
	<object>
		<name>label</name>
		<pose>Unspecified</pose>
		<truncated>0</truncated>
		<difficult>0</difficult>
		<occluded>0</occluded>
		<bndbox>
			<xmin>650</xmin>
			<xmax>795</xmax>
			<ymin>551</ymin>
			<ymax>588</ymax>
		</bndbox>
	</object>
</annotation>
